pyfuck
